cshelph.py
cshelph-2.9.0.data/scripts/cshelph.py
cshelph-2.9.0.dist-info/LICENSE.txt
cshelph-2.9.0.dist-info/METADATA
cshelph-2.9.0.dist-info/WHEEL
cshelph-2.9.0.dist-info/top_level.txt
cshelph-2.9.0.dist-info/RECORD
