Metadata-Version: 2.1
Name: cshelph
Version: 2.9.0
Summary: Classification of Sub-aquatic Height Extracted Photons
Home-page: https://github.com/nmt28/C-SHELPh
Author: Nathan Thomas and Brian Lee
Author-email: nmthomas28@gmail.com
License: LICENSE.txt
Classifier: Intended Audience :: Developers
Classifier: Intended Audience :: Science/Research
Classifier: Operating System :: OS Independent
Classifier: Programming Language :: Python :: 3
License-File: LICENSE.txt
